signaling/__init__.py
signaling/exceptions.py
signaling/signal.py
signaling-1.0.0.dist-info/DESCRIPTION.rst
signaling-1.0.0.dist-info/METADATA
signaling-1.0.0.dist-info/RECORD
signaling-1.0.0.dist-info/WHEEL
signaling-1.0.0.dist-info/metadata.json
signaling-1.0.0.dist-info/pbr.json
signaling-1.0.0.dist-info/top_level.txt
