Metadata-Version: 2.0
Name: signaling
Version: 1.0.0
Summary: Simple signal/slot implementation
Home-page: https://github.com/mdomke/signaling
Author: Martin Domke
Author-email: mail@martindomke.net
License: MIT
Platform: UNKNOWN
Classifier: Environment :: Console
Classifier: Intended Audience :: Developers
Classifier: License :: Other/Proprietary License
Classifier: Operating System :: POSIX :: Linux
Classifier: Operating System :: MacOS :: MacOS X
Classifier: Programming Language :: Python
Classifier: Programming Language :: Python :: 2
Classifier: Programming Language :: Python :: 3
Classifier: Topic :: Software Development :: Libraries
